wowmysql/__init__.py
wowmysql/client.py
wowmysql/table.py
wowmysql/types.py
wowmysql_sdk-2.0.0.dist-info/licenses/LICENSE
wowmysql_sdk-2.0.0.dist-info/METADATA
wowmysql_sdk-2.0.0.dist-info/WHEEL
wowmysql_sdk-2.0.0.dist-info/top_level.txt
wowmysql_sdk-2.0.0.dist-info/RECORD
