Metadata-Version: 2.4
Name: wowmysql-sdk
Version: 2.0.0
Summary: Official Python SDK for WowMySQL - MySQL Backend-as-a-Service
Home-page: https://github.com/wowmysql/wowmysql
Author: WowMySQL Team
Author-email: WowMySQL Team <support@wowmysql.com>
Project-URL: Homepage, https://wowmysql.com
Project-URL: Documentation, https://docs.wowmysql.com
Project-URL: Repository, https://github.com/wowmysql/wowmysql
Project-URL: Bug Tracker, https://github.com/wowmysql/wowmysql/issues
Keywords: wowmysql,mysql,database,backend-as-a-service,baas,api,rest
Classifier: Development Status :: 4 - Beta
Classifier: Intended Audience :: Developers
Classifier: Topic :: Software Development :: Libraries :: Python Modules
Classifier: License :: OSI Approved :: MIT License
Classifier: Programming Language :: Python :: 3
Classifier: Programming Language :: Python :: 3.8
Classifier: Programming Language :: Python :: 3.9
Classifier: Programming Language :: Python :: 3.10
Classifier: Programming Language :: Python :: 3.11
Classifier: Programming Language :: Python :: 3.12
Requires-Python: >=3.8
License-File: LICENSE
Requires-Dist: requests>=2.31.0
Requires-Dist: typing-extensions>=4.0.0
Provides-Extra: dev
Requires-Dist: pytest>=7.0.0; extra == "dev"
Requires-Dist: pytest-cov>=4.0.0; extra == "dev"
Requires-Dist: black>=23.0.0; extra == "dev"
Requires-Dist: mypy>=1.0.0; extra == "dev"
Dynamic: author
Dynamic: home-page
Dynamic: license-file
Dynamic: requires-python
